athena/__init__.py
athena/federation/__init__.py
athena/federation/athena_data_source.py
athena/federation/batch_writer.py
athena/federation/block_writer.py
athena/federation/data_catalog.py
athena/federation/lambda_handler.py
athena/federation/models.py
athena/federation/sdk.py
athena/federation/utils.py
unoffical_athena_federation_sdk-0.0.3.dist-info/LICENSE
unoffical_athena_federation_sdk-0.0.3.dist-info/METADATA
unoffical_athena_federation_sdk-0.0.3.dist-info/WHEEL
unoffical_athena_federation_sdk-0.0.3.dist-info/top_level.txt
unoffical_athena_federation_sdk-0.0.3.dist-info/RECORD
