Metadata-Version: 2.1
Name: unoffical-athena-federation-sdk
Version: 0.0.3
Summary: Unofficial Python SDK for Athena Federation
Home-page: https://github.com/dacort/athena-federation-python-sdk
License: UNKNOWN
Project-URL: Bug Tracker, https://github.com/dacort/athena-federation-python-sdk/issues
Platform: UNKNOWN
Classifier: Programming Language :: Python :: 3
Requires-Python: ~=3.8
License-File: LICENSE
Requires-Dist: pyarrow (==0.16.0)
Requires-Dist: smart-open (==5.2.1)
